openbox/__init__.py
openbox/__main__.py
openbox/py.typed
openbox/acq_optimizer/__init__.py
openbox/acq_optimizer/basic_maximizer.py
openbox/acq_optimizer/build.py
openbox/acq_optimizer/random_configuration_chooser.py
openbox/acquisition_function/__init__.py
openbox/acquisition_function/acquisition.py
openbox/acquisition_function/mc_acquisition.py
openbox/acquisition_function/mc_multi_objective_acquisition.py
openbox/acquisition_function/multi_objective_acquisition.py
openbox/apps/__init__.py
openbox/apps/multi_fidelity/__init__.py
openbox/apps/multi_fidelity/async_mq_base_facade.py
openbox/apps/multi_fidelity/async_mq_hb.py
openbox/apps/multi_fidelity/async_mq_hb_v0.py
openbox/apps/multi_fidelity/async_mq_hb_v2.py
openbox/apps/multi_fidelity/async_mq_mf_worker.py
openbox/apps/multi_fidelity/async_mq_mfes.py
openbox/apps/multi_fidelity/async_mq_sh.py
openbox/apps/multi_fidelity/async_mq_sh_v0.py
openbox/apps/multi_fidelity/async_mq_sh_v2.py
openbox/apps/multi_fidelity/mq_base_facade.py
openbox/apps/multi_fidelity/mq_bohb.py
openbox/apps/multi_fidelity/mq_hb.py
openbox/apps/multi_fidelity/mq_mf_worker.py
openbox/apps/multi_fidelity/mq_mfes.py
openbox/apps/multi_fidelity/mq_random_search.py
openbox/apps/multi_fidelity/utils.py
openbox/artifact/__init__.py
openbox/artifact/manage.py
openbox/artifact/remote_advisor.py
openbox/artifact/artifact/__init__.py
openbox/artifact/artifact/asgi.py
openbox/artifact/artifact/settings.py
openbox/artifact/artifact/test_task_done.py
openbox/artifact/artifact/test_task_register.py
openbox/artifact/artifact/urls.py
openbox/artifact/artifact/wsgi.py
openbox/artifact/bo_advice/__init__.py
openbox/artifact/bo_advice/admin.py
openbox/artifact/bo_advice/apps.py
openbox/artifact/bo_advice/models.py
openbox/artifact/bo_advice/tests.py
openbox/artifact/bo_advice/urls.py
openbox/artifact/bo_advice/views.py
openbox/artifact/bo_advice/migrations/0001_initial.py
openbox/artifact/bo_advice/migrations/__init__.py
openbox-0.8.4.dist-info/LICENSE
openbox-0.8.4.dist-info/METADATA
openbox-0.8.4.dist-info/WHEEL
openbox-0.8.4.dist-info/entry_points.txt
openbox-0.8.4.dist-info/top_level.txt
openbox-0.8.4.dist-info/RECORD
