Metadata-Version: 2.1
Name: openbox
Version: 0.8.4
Summary: Efficient and generalized blackbox optimization (BBO) system
Author: DAIR Lab @ Peking University
Maintainer-email: Yang Li <liyang.cs@pku.edu.cn>, Huaijun Jiang <jianghuaijun@pku.edu.cn>, Yu Shen <shenyu@pku.edu.cn>
License: MIT License
Project-URL: GitHub, https://github.com/PKU-DAIR/open-box
Project-URL: Bug Tracker, https://github.com/PKU-DAIR/open-box/issues
Project-URL: Documentation, https://open-box.readthedocs.io/
Project-URL: PyPI, https://pypi.org/project/openbox/
Keywords: blackbox optimization,Bayesian optimization,hyperparameter optimization,automated machine learning,multi-objective optimization,constrained optimization
Classifier: Programming Language :: Python :: 3
Requires-Python: >=3.7
License-File: LICENSE
Requires-Dist: cython
Requires-Dist: psutil
Requires-Dist: setuptools
Requires-Dist: requests
Requires-Dist: tqdm
Requires-Dist: prettytable
Requires-Dist: colorama
Requires-Dist: matplotlib
Requires-Dist: pandas
Requires-Dist: numpy >=1.7.1
Requires-Dist: scipy <=1.10.1,>=0.18.1
Requires-Dist: scikit-learn <=1.5.1,>=0.21.3
Requires-Dist: scikit-optimize >=0.9
Requires-Dist: ConfigSpace <=0.6.1,>=0.4.20
Requires-Dist: emcee
Requires-Dist: statsmodels
Requires-Dist: platypus-opt ==1.0.4
Provides-Extra: build
Requires-Dist: setuptools >=61.0 ; extra == 'build'
Requires-Dist: build ; extra == 'build'
Requires-Dist: wheel ; extra == 'build'
Requires-Dist: twine ; extra == 'build'
Provides-Extra: dev
Requires-Dist: pytest >=6.0 ; extra == 'dev'
Requires-Dist: pytest-cov ; extra == 'dev'
Requires-Dist: docutils >=0.17 ; extra == 'dev'
Requires-Dist: sphinx ; extra == 'dev'
Requires-Dist: myst-parser ; extra == 'dev'
Requires-Dist: linkify-it-py ; extra == 'dev'
Requires-Dist: furo ; extra == 'dev'
Requires-Dist: sphinx-copybutton ; extra == 'dev'
Requires-Dist: sphinx-notfound-page ; extra == 'dev'
Requires-Dist: sphinx-hoverxref ; extra == 'dev'
Requires-Dist: setuptools >=61.0 ; extra == 'dev'
Requires-Dist: build ; extra == 'dev'
Requires-Dist: wheel ; extra == 'dev'
Requires-Dist: twine ; extra == 'dev'
Provides-Extra: docs
Requires-Dist: docutils >=0.17 ; extra == 'docs'
Requires-Dist: sphinx ; extra == 'docs'
Requires-Dist: myst-parser ; extra == 'docs'
Requires-Dist: linkify-it-py ; extra == 'docs'
Requires-Dist: furo ; extra == 'docs'
Requires-Dist: sphinx-copybutton ; extra == 'docs'
Requires-Dist: sphinx-notfound-page ; extra == 'docs'
Requires-Dist: sphinx-hoverxref ; extra == 'docs'
Provides-Extra: extra
Requires-Dist: pyrfr ; extra == 'extra'
Requires-Dist: shap ; extra == 'extra'
Requires-Dist: lightgbm ; extra == 'extra'
Requires-Dist: hiplot ; extra == 'extra'
Requires-Dist: cma ; extra == 'extra'
Requires-Dist: xgboost ; extra == 'extra'
Provides-Extra: format
Provides-Extra: service
Requires-Dist: django >=2.2.17 ; extra == 'service'
Requires-Dist: pymongo <4.0 ; extra == 'service'
Requires-Dist: bson ; extra == 'service'
Requires-Dist: pyjwt ; extra == 'service'
Requires-Dist: pyrfr ; extra == 'service'
Requires-Dist: shap ; extra == 'service'
Requires-Dist: lightgbm ; extra == 'service'
Requires-Dist: hiplot ; extra == 'service'
Requires-Dist: cma ; extra == 'service'
Requires-Dist: xgboost ; extra == 'service'
Provides-Extra: test
Requires-Dist: pytest >=6.0 ; extra == 'test'
Requires-Dist: pytest-cov ; extra == 'test'
